README.md
setup.py
sed/__init__.py
sed.egg-info/PKG-INFO
sed.egg-info/SOURCES.txt
sed.egg-info/dependency_links.txt
sed.egg-info/not-zip-safe
sed.egg-info/top_level.txt
sed/engine/StreamEditor.py
sed/engine/__init__.py
sed/engine/match_engine.py
sed/engine/sed_file_util.py
sed/engine/sed_regex.py
sed/engine/sed_util.py