Metadata-Version: 1.1
Name: sed
Version: 0.3.1
Summary: Streaming editor toolkit
Home-page: http://iwebthereforeiam.com
Author: Hugh Brown
Author-email: hughdbrown@yahoo.com
License: MIT
Platform: UNKNOWN
Classifier: Development Status :: 3 - Alpha
Classifier: Intended Audience :: Developers
Classifier: License :: OSI Approved :: MIT License
Classifier: Programming Language :: Python
Classifier: Programming Language :: Python :: 2
Classifier: Programming Language :: Python :: 3
Classifier: Topic :: Software Development :: Libraries :: Python Modules
